README.md
setup.py
ArPyLearning/__init__.py
ArPyLearning/arduino.py
ArPyLearning.egg-info/PKG-INFO
ArPyLearning.egg-info/SOURCES.txt
ArPyLearning.egg-info/dependency_links.txt
ArPyLearning.egg-info/requires.txt
ArPyLearning.egg-info/top_level.txt